[
  {
    "predicate": {
      "item": "druidcraft:moonstone_shovel"
    },
    "item": "tetra:modular_single",
    "modules": {
      "single/head": ["single/basic_shovel", "basic_shovel/moonstone"],
      "single/handle": ["single/basic_handle", "basic_handle/stick"]
    },
    "improvements": {
      "single/head:tetrapak/moonstrike": 1,
      "single/head:arrested": 0
    }
  },
  {
    "predicate": {
      "item": "druidcraft:moonstone_sword"
    },
    "item": "tetra:modular_sword",
    "modules": {
      "sword/blade": ["sword/basic_blade", "basic_blade/moonstone"],
      "sword/hilt": ["sword/basic_hilt", "basic_hilt/stick"],
      "sword/pommel": ["sword/decorative_pommel", "decorative_pommel/moonstone"],
      "sword/guard": ["sword/makeshift_guard", "makeshift_guard/moonstone"]
    },
    "improvements": {
      "sword/blade:tetrapak/moonstrike": 1,
      "sword/blade:arrested": 0
    }
  },
  {
    "predicate": {
      "item": "druidcraft:moonstone_pickaxe"
    },
    "item": "tetra:modular_double",
    "modules": {
      "double/head_left": ["double/basic_pickaxe_left", "basic_pickaxe/moonstone"],
      "double/head_right": ["double/basic_pickaxe_right", "basic_pickaxe/moonstone"],
      "double/handle": ["double/basic_handle", "basic_handle/stick"]
    },
    "improvements": {
      "double/head_left:tetrapak/moonstrike": 1,
      "double/head_right:tetrapak/moonstrike": 1,
      "double/head_left:arrested": 0,
      "double/head_right:arrested": 0
    }
  },
  {
    "predicate": {
      "item": "druidcraft:moonstone_axe"
    },
    "item": "tetra:modular_double",
    "modules": {
      "double/head_left": ["double/basic_axe_left", "basic_axe/moonstone"],
      "double/head_right": ["double/butt_right", "butt/moonstone"],
      "double/handle": ["double/basic_handle", "basic_handle/stick"]
    },
    "improvements": {
      "double/head_left:tetrapak/moonstrike": 1,
      "double/head_right:tetrapak/moonstrike": 1,
      "double/head_left:arrested": 0,
      "double/head_right:arrested": 0
    }
  },
  {
    "predicate": {
      "item": "druidcraft:moonstone_hoe"
    },
    "item": "tetra:modular_double",
    "modules": {
      "double/head_left": ["double/hoe_left", "hoe/moonstone"],
      "double/head_right": ["double/butt_right", "butt/moonstone"],
      "double/handle": ["double/basic_handle", "basic_handle/stick"]
    },
    "improvements": {
      "double/head_left:tetrapak/moonstrike": 1,
      "double/head_right:tetrapak/moonstrike": 1,
      "double/head_left:arrested": 0,
      "double/head_right:arrested": 0
    }
  }
]